cloud_scanner_azure/__init__.py
cloud_scanner_azure/version.py
cloud_scanner_azure/config/__init__.py
cloud_scanner_azure/config/azure_config.py
cloud_scanner_azure/config/azure_cosmosdb_config.py
cloud_scanner_azure/config/azure_credential_config.py
cloud_scanner_azure/config/azure_resource_config.py
cloud_scanner_azure/config/azure_storage_config.py
cloud_scanner_azure/helpers/__init__.py
cloud_scanner_azure/helpers/extractors.py
cloud_scanner_azure/services/__init__.py
cloud_scanner_azure/services/azure_cosmosdb.py
cloud_scanner_azure/services/azure_resource.py
cloud_scanner_azure/services/azure_resource_service.py
cloud_scanner_azure/services/azure_storage_container.py
cloud_scanner_azure/services/azure_storage_queue.py
cloud_scanner_azure/services/azure_subscription_service.py
tests/__init__.py
tests/test_azure_config.py
tests/test_extractors.py
tests/test_filter.py
tests/test_integration.py
tests/test_resource_object.py
tests/unittest_base.py
cloud_scanner_azure-0.1.2.dist-info/LICENSE
cloud_scanner_azure-0.1.2.dist-info/METADATA
cloud_scanner_azure-0.1.2.dist-info/WHEEL
cloud_scanner_azure-0.1.2.dist-info/top_level.txt
cloud_scanner_azure-0.1.2.dist-info/RECORD
