Metadata-Version: 2.1
Name: cloud-scanner-azure
Version: 0.1.2
Summary: Core package for scanning Azure cloud resources
Home-page: https://microsoft.github.io/cloud-scanner-azure
Author: Microsoft
Author-email: tanner.barlow@microsoft.com,wallace.breza@microsoft.com
License: MIT
Platform: UNKNOWN
Requires-Dist: azure-mgmt-nspkg
Requires-Dist: azure-mgmt-resource
Requires-Dist: azure-mgmt-subscription
Requires-Dist: azure-servicebus
Requires-Dist: azure-storage
Requires-Dist: azure-storage-common
Requires-Dist: azure-cosmosdb-table
Requires-Dist: azure-functions
